testball/__init__.py
testball/player.py
testball/team.py
testball/team_wl.py
testball-0.0.0.1.dist-info/METADATA
testball-0.0.0.1.dist-info/WHEEL
testball-0.0.0.1.dist-info/top_level.txt
testball-0.0.0.1.dist-info/RECORD
